supervisor/__init__.py
supervisor/exceptions.py
supervisor/saving.py
supervisor/version.py
supervisor/api/__init__.py
supervisor/api/defaults.py
supervisor/api/interfaces.py
supervisor/api/tests/__init__.py
supervisor/api/tests/test_interfaces.py
supervisor/confidence/__init__.py
supervisor/confidence/model_linearity.py
supervisor/confidence/trustscore.py
supervisor/confidence/tests/__init__.py
supervisor/confidence/tests/test_model_linearity.py
supervisor/confidence/tests/test_trustscore.py
supervisor/data/cats.tar.gz
supervisor/datasets/__init__.py
supervisor/datasets/default.py
supervisor/datasets/tensorflow.py
supervisor/datasets/tests/__init__.py
supervisor/datasets/tests/test_datasets.py
supervisor/explainers/__init__.py
supervisor/explainers/ale.py
supervisor/explainers/cem.py
supervisor/explainers/cfproto.py
supervisor/explainers/cfrl_base.py
supervisor/explainers/cfrl_tabular.py
supervisor/explainers/counterfactual.py
supervisor/explainers/integrated_gradients.py
supervisor/explainers/partial_dependence.py
supervisor/explainers/pd_variance.py
supervisor/explainers/permutation_importance.py
supervisor/explainers/shap_wrappers.py
supervisor/explainers/anchors/__init__.py
supervisor/explainers/anchors/anchor_base.py
supervisor/explainers/anchors/anchor_explanation.py
supervisor/explainers/anchors/anchor_image.py
supervisor/explainers/anchors/anchor_tabular.py
supervisor/explainers/anchors/anchor_tabular_distributed.py
supervisor/explainers/anchors/anchor_text.py
supervisor/explainers/anchors/language_model_text_sampler.py
supervisor/explainers/anchors/text_samplers.py
supervisor/explainers/backends/__init__.py
supervisor/explainers/backends/cfrl_base.py
supervisor/explainers/backends/cfrl_tabular.py
supervisor/explainers/backends/pytorch/__init__.py
supervisor/explainers/backends/pytorch/cfrl_base.py
supervisor/explainers/backends/pytorch/cfrl_tabular.py
supervisor/explainers/backends/tensorflow/__init__.py
kozmo_supervisor-0.1.0.dist-info/LICENSE
kozmo_supervisor-0.1.0.dist-info/METADATA
kozmo_supervisor-0.1.0.dist-info/WHEEL
kozmo_supervisor-0.1.0.dist-info/top_level.txt
kozmo_supervisor-0.1.0.dist-info/RECORD
